{"ongoing_trials": {}, "hyperparameters": {"space": [{"class_name": "Choice", "config": {"name": "embedding_dim", "default": 32, "conditions": [], "values": [32, 64, 128], "ordered": true}}, {"class_name": "Choice", "config": {"name": "lstm_units", "default": 64, "conditions": [], "values": [64, 128, 256], "ordered": true}}, {"class_name": "Float", "config": {"name": "dropout_rate", "default": 0.2, "conditions": [], "min_value": 0.2, "max_value": 0.5, "step": 0.1, "sampling": "linear"}}, {"class_name": "Float", "config": {"name": "learning_rate", "default": 0.0001, "conditions": [], "min_value": 0.0001, "max_value": 0.01, "step": null, "sampling": "log"}}], "values": {"embedding_dim": 32, "lstm_units": 64, "dropout_rate": 0.2, "learning_rate": 0.0001}}, "start_order": ["0", "1", "2", "3", "4"], "end_order": ["0", "1", "2", "3", "4"], "run_times": {"0": 1, "1": 1, "2": 1, "3": 1, "4": 1}, "retry_queue": [], "seed": 7025, "seed_state": 7045, "tried_so_far": ["334c921a80a5e32629d2a380b9893b9e", "085535310ccbae036f9d970facf0d7f1", "cbaf67743126dea114e59bd5421420a8", "d8aae4a82a49e4d404032b3c5fa76735", "66b7af874cdcde8365ff51930dbf473c"], "id_to_hash": {"0": "cbaf67743126dea114e59bd5421420a8", "1": "085535310ccbae036f9d970facf0d7f1", "2": "d8aae4a82a49e4d404032b3c5fa76735", "3": "334c921a80a5e32629d2a380b9893b9e", "4": "66b7af874cdcde8365ff51930dbf473c"}, "display": {"search_start": "2025-08-15T08:33:01.384128", "trial_start": {"0": "2025-08-15T08:33:01.384128", "1": "2025-08-15T08:40:04.880792", "2": "2025-08-15T08:42:00.890480", "3": "2025-08-15T08:50:01.624680", "4": "2025-08-15T08:53:21.660672"}, "trial_number": {"0": 1, "1": 2, "2": 3, "3": 4, "4": 5}}}